threecxapi/__init__.py
threecxapi/_version.py
threecxapi/connection.py
threecxapi/exceptions.py
threecxapi/util.py
threecxapi/components/__init__.py
threecxapi/components/parameters.py
threecxapi/components/response.py
threecxapi/components/schema.py
threecxapi/components/responses/__init__.py
threecxapi/components/responses/other.py
threecxapi/components/responses/pbx.py
threecxapi/components/schemas/__init__.py
threecxapi/components/schemas/_schemas.py
threecxapi/components/schemas/pbx/__init__.py
threecxapi/components/schemas/pbx/_pbx.py
threecxapi/components/schemas/pbx/enums.py
threecxapi/components/schemas/pbx/ODataErrors/ODataErrors.py
threecxapi/components/schemas/pbx/ODataErrors/__init__.py
threecxapi/resources/__init__.py
threecxapi/resources/api_resource.py
threecxapi/resources/groups.py
threecxapi/resources/peers.py
threecxapi/resources/trunks.py
threecxapi/resources/users.py
threecxapi/resources/exceptions/__init__.py
threecxapi/resources/exceptions/groups_exceptions.py
threecxapi/resources/exceptions/peers_exceptions.py
threecxapi/resources/exceptions/trunks_exceptions.py
threecxapi/resources/exceptions/users_exceptions.py
threecxapi/tests/conftest.py
threecxapi/tests/test_exceptions.py
threecxapi/tests/test_tcx_api_connection.py
threecxapi/tests/components/test_parameters.py
threecxapi/tests/resources/test_groups.py
threecxapi/tests/resources/test_users.py
threecxapi/tests/util/test_util.py
threecxapi-1.0.6.dist-info/licenses/LICENSE
threecxapi-1.0.6.dist-info/METADATA
threecxapi-1.0.6.dist-info/WHEEL
threecxapi-1.0.6.dist-info/top_level.txt
threecxapi-1.0.6.dist-info/RECORD
