Metadata-Version: 2.4
Name: threecxapi
Version: 1.0.6
Summary: This is a python wrapper for the 3CX API. It is designed to make it easier to interact with the 3CX API. It is a work in progress and is not yet feature complete. It is designed to be used with the official 3CX v20 API.
Author-email: Matt Henry <matthttam@gmail.com>
License-Expression: GPL-3.0-or-later
Project-URL: Home, https://github.com/matthttam/ThreeCXAPI
Classifier: Programming Language :: Python :: 3
Requires-Python: >=3.12
License-File: LICENSE
Dynamic: license-file
